<?xml version="1.0" encoding="utf-8" ?>
<dwsync>
<file name="superbox-full-1.jpg" server="Macintosh HD/Applications/XAMPP/xamppfiles/htdocs/myta/" local="3467763646" remote="318763443860660158" Dst="-1" />
<file name="superbox-full-10.jpg" server="Macintosh HD/Applications/XAMPP/xamppfiles/htdocs/myta/" local="3467763646" remote="318763443860660158" Dst="-1" />
<file name="superbox-full-11.jpg" server="Macintosh HD/Applications/XAMPP/xamppfiles/htdocs/myta/" local="3467763646" remote="318763443860660158" Dst="-1" />
<file name="superbox-full-12.jpg" server="Macintosh HD/Applications/XAMPP/xamppfiles/htdocs/myta/" local="3467763646" remote="318763443860660158" Dst="-1" />
<file name="superbox-full-13.jpg" server="Macintosh HD/Applications/XAMPP/xamppfiles/htdocs/myta/" local="3467763646" remote="318763443860660158" Dst="-1" />
<file name="superbox-full-14.jpg" server="Macintosh HD/Applications/XAMPP/xamppfiles/htdocs/myta/" local="3467763646" remote="318763443860660158" Dst="-1" />
<file name="superbox-full-15.jpg" server="Macintosh HD/Applications/XAMPP/xamppfiles/htdocs/myta/" local="3467763646" remote="318763443860660158" Dst="-1" />
<file name="superbox-full-16.jpg" server="Macintosh HD/Applications/XAMPP/xamppfiles/htdocs/myta/" local="3467763646" remote="318763443860660158" Dst="-1" />
<file name="superbox-full-17.jpg" server="Macintosh HD/Applications/XAMPP/xamppfiles/htdocs/myta/" local="3467763646" remote="318763443860660158" Dst="-1" />
<file name="superbox-full-18.jpg" server="Macintosh HD/Applications/XAMPP/xamppfiles/htdocs/myta/" local="3467763646" remote="318763443860660158" Dst="-1" />
<file name="superbox-full-19.jpg" server="Macintosh HD/Applications/XAMPP/xamppfiles/htdocs/myta/" local="3467763646" remote="318763443860660158" Dst="-1" />
<file name="superbox-full-2.jpg" server="Macintosh HD/Applications/XAMPP/xamppfiles/htdocs/myta/" local="3467763646" remote="318763443860660158" Dst="-1" />
<file name="superbox-full-20-bw.jpg" server="Macintosh HD/Applications/XAMPP/xamppfiles/htdocs/myta/" local="3483870408" remote="318763443876766920" Dst="-1" />
<file name="superbox-full-20.jpg" server="Macintosh HD/Applications/XAMPP/xamppfiles/htdocs/myta/" local="3467763646" remote="318763443860660158" Dst="-1" />
<file name="superbox-full-21.jpg" server="Macintosh HD/Applications/XAMPP/xamppfiles/htdocs/myta/" local="3467763646" remote="318763443860660158" Dst="-1" />
<file name="superbox-full-22.jpg" server="Macintosh HD/Applications/XAMPP/xamppfiles/htdocs/myta/" local="3467763646" remote="318763443860660158" Dst="-1" />
<file name="superbox-full-23.jpg" server="Macintosh HD/Applications/XAMPP/xamppfiles/htdocs/myta/" local="3467763646" remote="318763443860660158" Dst="-1" />
<file name="superbox-full-24.jpg" server="Macintosh HD/Applications/XAMPP/xamppfiles/htdocs/myta/" local="3467763646" remote="318763443860660158" Dst="-1" />
<file name="superbox-full-3.jpg" server="Macintosh HD/Applications/XAMPP/xamppfiles/htdocs/myta/" local="3467763646" remote="318763443860660158" Dst="-1" />
<file name="superbox-full-4.jpg" server="Macintosh HD/Applications/XAMPP/xamppfiles/htdocs/myta/" local="3467763646" remote="318763443860660158" Dst="-1" />
<file name="superbox-full-5.jpg" server="Macintosh HD/Applications/XAMPP/xamppfiles/htdocs/myta/" local="3467763646" remote="318763443860660158" Dst="-1" />
<file name="superbox-full-6.jpg" server="Macintosh HD/Applications/XAMPP/xamppfiles/htdocs/myta/" local="3467763646" remote="318763443860660158" Dst="-1" />
<file name="superbox-full-7.jpg" server="Macintosh HD/Applications/XAMPP/xamppfiles/htdocs/myta/" local="3467763646" remote="318763443860660158" Dst="-1" />
<file name="superbox-full-8.jpg" server="Macintosh HD/Applications/XAMPP/xamppfiles/htdocs/myta/" local="3467763646" remote="318763443860660158" Dst="-1" />
<file name="superbox-full-9.jpg" server="Macintosh HD/Applications/XAMPP/xamppfiles/htdocs/myta/" local="3467763646" remote="318763443860660158" Dst="-1" />
<file name="superbox-thumb-1.jpg" server="Macintosh HD/Applications/XAMPP/xamppfiles/htdocs/myta/" local="3467763646" remote="318763443860660158" Dst="-1" />
<file name="superbox-thumb-10.jpg" server="Macintosh HD/Applications/XAMPP/xamppfiles/htdocs/myta/" local="3467763646" remote="318763443860660158" Dst="-1" />
<file name="superbox-thumb-11.jpg" server="Macintosh HD/Applications/XAMPP/xamppfiles/htdocs/myta/" local="3467763646" remote="318763443860660158" Dst="-1" />
<file name="superbox-thumb-12.jpg" server="Macintosh HD/Applications/XAMPP/xamppfiles/htdocs/myta/" local="3467763646" remote="318763443860660158" Dst="-1" />
<file name="superbox-thumb-13.jpg" server="Macintosh HD/Applications/XAMPP/xamppfiles/htdocs/myta/" local="3467763646" remote="318763443860660158" Dst="-1" />
<file name="superbox-thumb-14.jpg" server="Macintosh HD/Applications/XAMPP/xamppfiles/htdocs/myta/" local="3467763646" remote="318763443860660158" Dst="-1" />
<file name="superbox-thumb-15.jpg" server="Macintosh HD/Applications/XAMPP/xamppfiles/htdocs/myta/" local="3467763646" remote="318763443860660158" Dst="-1" />
<file name="superbox-thumb-16.jpg" server="Macintosh HD/Applications/XAMPP/xamppfiles/htdocs/myta/" local="3467763646" remote="318763443860660158" Dst="-1" />
<file name="superbox-thumb-17.jpg" server="Macintosh HD/Applications/XAMPP/xamppfiles/htdocs/myta/" local="3467763646" remote="318763443860660158" Dst="-1" />
<file name="superbox-thumb-18.jpg" server="Macintosh HD/Applications/XAMPP/xamppfiles/htdocs/myta/" local="3467763646" remote="318763443860660158" Dst="-1" />
<file name="superbox-thumb-19.jpg" server="Macintosh HD/Applications/XAMPP/xamppfiles/htdocs/myta/" local="3467763646" remote="318763443860660158" Dst="-1" />
<file name="superbox-thumb-2.jpg" server="Macintosh HD/Applications/XAMPP/xamppfiles/htdocs/myta/" local="3467763646" remote="318763443860660158" Dst="-1" />
<file name="superbox-thumb-20.jpg" server="Macintosh HD/Applications/XAMPP/xamppfiles/htdocs/myta/" local="3467763646" remote="318763443860660158" Dst="-1" />
<file name="superbox-thumb-21.jpg" server="Macintosh HD/Applications/XAMPP/xamppfiles/htdocs/myta/" local="3467763646" remote="318763443860660158" Dst="-1" />
<file name="superbox-thumb-22.jpg" server="Macintosh HD/Applications/XAMPP/xamppfiles/htdocs/myta/" local="3467763646" remote="318763443860660158" Dst="-1" />
<file name="superbox-thumb-23.jpg" server="Macintosh HD/Applications/XAMPP/xamppfiles/htdocs/myta/" local="3467763646" remote="318763443860660158" Dst="-1" />
<file name="superbox-thumb-24.jpg" server="Macintosh HD/Applications/XAMPP/xamppfiles/htdocs/myta/" local="3467763646" remote="318763443860660158" Dst="-1" />
<file name="superbox-thumb-3.jpg" server="Macintosh HD/Applications/XAMPP/xamppfiles/htdocs/myta/" local="3467763646" remote="318763443860660158" Dst="-1" />
<file name="superbox-thumb-4.jpg" server="Macintosh HD/Applications/XAMPP/xamppfiles/htdocs/myta/" local="3467763646" remote="318763443860660158" Dst="-1" />
<file name="superbox-thumb-5.jpg" server="Macintosh HD/Applications/XAMPP/xamppfiles/htdocs/myta/" local="3467763646" remote="318763443860660158" Dst="-1" />
<file name="superbox-thumb-6.jpg" server="Macintosh HD/Applications/XAMPP/xamppfiles/htdocs/myta/" local="3467763646" remote="318763443860660158" Dst="-1" />
<file name="superbox-thumb-7.jpg" server="Macintosh HD/Applications/XAMPP/xamppfiles/htdocs/myta/" local="3467763646" remote="318763443860660158" Dst="-1" />
<file name="superbox-thumb-8.jpg" server="Macintosh HD/Applications/XAMPP/xamppfiles/htdocs/myta/" local="3467763646" remote="318763443860660158" Dst="-1" />
<file name="superbox-thumb-9.jpg" server="Macintosh HD/Applications/XAMPP/xamppfiles/htdocs/myta/" local="3467763646" remote="318763443860660158" Dst="-1" />
<file name="superbox-full-1.jpg" server="D:/XAMPP/htdocs/mytasource/" local="130778090260000000" remote="130778090260000000" Dst="0" />
<file name="superbox-full-10.jpg" server="D:/XAMPP/htdocs/mytasource/" local="130778090280000000" remote="130778090280000000" Dst="0" />
<file name="superbox-full-11.jpg" server="D:/XAMPP/htdocs/mytasource/" local="130778090300000000" remote="130778090300000000" Dst="0" />
<file name="superbox-full-12.jpg" server="D:/XAMPP/htdocs/mytasource/" local="130778090320000000" remote="130778090320000000" Dst="0" />
<file name="superbox-full-13.jpg" server="D:/XAMPP/htdocs/mytasource/" local="130778090360000000" remote="130778090360000000" Dst="0" />
<file name="superbox-full-14.jpg" server="D:/XAMPP/htdocs/mytasource/" local="130778090380000000" remote="130778090380000000" Dst="0" />
<file name="superbox-full-15.jpg" server="D:/XAMPP/htdocs/mytasource/" local="130778090400000000" remote="130778090400000000" Dst="0" />
<file name="superbox-full-16.jpg" server="D:/XAMPP/htdocs/mytasource/" local="130778090420000000" remote="130778090420000000" Dst="0" />
<file name="superbox-full-17.jpg" server="D:/XAMPP/htdocs/mytasource/" local="130778090440000000" remote="130778090440000000" Dst="0" />
<file name="superbox-full-18.jpg" server="D:/XAMPP/htdocs/mytasource/" local="130778090480000000" remote="130778090480000000" Dst="0" />
<file name="superbox-full-19.jpg" server="D:/XAMPP/htdocs/mytasource/" local="130778090500000000" remote="130778090500000000" Dst="0" />
<file name="superbox-full-2.jpg" server="D:/XAMPP/htdocs/mytasource/" local="130778090520000000" remote="130778090520000000" Dst="0" />
<file name="superbox-full-20-bw.jpg" server="D:/XAMPP/htdocs/mytasource/" local="130778090540000000" remote="130778090540000000" Dst="0" />
<file name="superbox-full-20.jpg" server="D:/XAMPP/htdocs/mytasource/" local="130778090560000000" remote="130778090560000000" Dst="0" />
<file name="superbox-full-21.jpg" server="D:/XAMPP/htdocs/mytasource/" local="130778090580000000" remote="130778090580000000" Dst="0" />
<file name="superbox-full-22.jpg" server="D:/XAMPP/htdocs/mytasource/" local="130778090620000000" remote="130778090620000000" Dst="0" />
<file name="superbox-full-23.jpg" server="D:/XAMPP/htdocs/mytasource/" local="130778090640000000" remote="130778090640000000" Dst="0" />
<file name="superbox-full-24.jpg" server="D:/XAMPP/htdocs/mytasource/" local="130778090660000000" remote="130778090660000000" Dst="0" />
<file name="superbox-full-3.jpg" server="D:/XAMPP/htdocs/mytasource/" local="130778090680000000" remote="130778090680000000" Dst="0" />
<file name="superbox-full-4.jpg" server="D:/XAMPP/htdocs/mytasource/" local="130778090700000000" remote="130778090700000000" Dst="0" />
<file name="superbox-full-5.jpg" server="D:/XAMPP/htdocs/mytasource/" local="130778090720000000" remote="130778090720000000" Dst="0" />
<file name="superbox-full-6.jpg" server="D:/XAMPP/htdocs/mytasource/" local="130778090740000000" remote="130778090740000000" Dst="0" />
<file name="superbox-full-7.jpg" server="D:/XAMPP/htdocs/mytasource/" local="130778090780000000" remote="130778090780000000" Dst="0" />
<file name="superbox-full-8.jpg" server="D:/XAMPP/htdocs/mytasource/" local="130778090800000000" remote="130778090800000000" Dst="0" />
<file name="superbox-full-9.jpg" server="D:/XAMPP/htdocs/mytasource/" local="130778090820000000" remote="130778090820000000" Dst="0" />
<file name="superbox-thumb-1.jpg" server="D:/XAMPP/htdocs/mytasource/" local="130778090840000000" remote="130778090840000000" Dst="0" />
<file name="superbox-thumb-10.jpg" server="D:/XAMPP/htdocs/mytasource/" local="130778090860000000" remote="130778090860000000" Dst="0" />
<file name="superbox-thumb-11.jpg" server="D:/XAMPP/htdocs/mytasource/" local="130778090880000000" remote="130778090880000000" Dst="0" />
<file name="superbox-thumb-12.jpg" server="D:/XAMPP/htdocs/mytasource/" local="130778090920000000" remote="130778090920000000" Dst="0" />
<file name="superbox-thumb-13.jpg" server="D:/XAMPP/htdocs/mytasource/" local="130778090940000000" remote="130778090940000000" Dst="0" />
<file name="superbox-thumb-14.jpg" server="D:/XAMPP/htdocs/mytasource/" local="130778090960000000" remote="130778090960000000" Dst="0" />
<file name="superbox-thumb-15.jpg" server="D:/XAMPP/htdocs/mytasource/" local="130778090980000000" remote="130778090980000000" Dst="0" />
<file name="superbox-thumb-16.jpg" server="D:/XAMPP/htdocs/mytasource/" local="130778091000000000" remote="130778091000000000" Dst="0" />
<file name="superbox-thumb-17.jpg" server="D:/XAMPP/htdocs/mytasource/" local="130778091020000000" remote="130778091020000000" Dst="0" />
<file name="superbox-thumb-18.jpg" server="D:/XAMPP/htdocs/mytasource/" local="130778091040000000" remote="130778091040000000" Dst="0" />
<file name="superbox-thumb-19.jpg" server="D:/XAMPP/htdocs/mytasource/" local="130778091060000000" remote="130778091060000000" Dst="0" />
<file name="superbox-thumb-2.jpg" server="D:/XAMPP/htdocs/mytasource/" local="130778091080000000" remote="130778091080000000" Dst="0" />
<file name="superbox-thumb-20.jpg" server="D:/XAMPP/htdocs/mytasource/" local="130778091100000000" remote="130778091100000000" Dst="0" />
<file name="superbox-thumb-21.jpg" server="D:/XAMPP/htdocs/mytasource/" local="130778091120000000" remote="130778091120000000" Dst="0" />
<file name="superbox-thumb-22.jpg" server="D:/XAMPP/htdocs/mytasource/" local="130778091160000000" remote="130778091160000000" Dst="0" />
<file name="superbox-thumb-23.jpg" server="D:/XAMPP/htdocs/mytasource/" local="130778091180000000" remote="130778091180000000" Dst="0" />
<file name="superbox-thumb-24.jpg" server="D:/XAMPP/htdocs/mytasource/" local="130778091200000000" remote="130778091200000000" Dst="0" />
<file name="superbox-thumb-3.jpg" server="D:/XAMPP/htdocs/mytasource/" local="130778091220000000" remote="130778091220000000" Dst="0" />
<file name="superbox-thumb-4.jpg" server="D:/XAMPP/htdocs/mytasource/" local="130778091240000000" remote="130778091240000000" Dst="0" />
<file name="superbox-thumb-5.jpg" server="D:/XAMPP/htdocs/mytasource/" local="130778091260000000" remote="130778091260000000" Dst="0" />
<file name="superbox-thumb-6.jpg" server="D:/XAMPP/htdocs/mytasource/" local="130778091280000000" remote="130778091280000000" Dst="0" />
<file name="superbox-thumb-7.jpg" server="D:/XAMPP/htdocs/mytasource/" local="130778091300000000" remote="130778091300000000" Dst="0" />
<file name="superbox-thumb-8.jpg" server="D:/XAMPP/htdocs/mytasource/" local="130778091340000000" remote="130778091340000000" Dst="0" />
<file name="superbox-thumb-9.jpg" server="D:/XAMPP/htdocs/mytasource/" local="130778091360000000" remote="130778091360000000" Dst="0" />
</dwsync>